{"category":"Tech","view_count":"29263","video_description":"Prestigio Multipad PMP5080B Tablet - GAMES. The Prestigio Multipad PMP5080B is a 8\" tablet with a capacitive multi- touchscreen (800x600) running Android 2.3 on a Rockchip RK2918 SoC. A extensive review can be found at Notebookcheck.com (DE) and Notebookcheck.net (EN).","title":"Prestigio Multipad PMP5080B Tablet - GAMES","avg_rating":"4.2","video_id":"viOkvmWavz0","video_type":"review","comments":[{"text":"can i handle some stronger games like order and chaos,\ufeff or asphalt 5 or 6","published":"2011-11-19T10:07:26.000Z","id":"dSFa_mbo1OqRMVNbTep7-HD5VpomLzGThG4pVoBMwvc","author":"warlock629","annotation":{"product-related":"1","rating":"2"}}],"uploader":"NotebookcheckReviews","published":"2011-10-17T21:24:08.000Z","duration":"151"}